Workbook

Sheet Содержание
A1: Задания для самостоятельной работы: Excel 2010 в примерах (уроки 1–9)
A3: 1.1 | B3: Продажи автомобилей + диаграмма
A4: 1.2 | B4: Сортировка по убыванию
A5: 2.1 | B5: Три диаграммы
A6: 2.2 | B6: Таблица выпускников + диаграмма
A7: 3.1 | B7: Поступление, сортировка по баллу
A8: 3.2 | B8: Список группы, фильтр иногородних
A9: 3.3 | B9: План поставки + диаграмма
A10: 4.1 | B10: Цены на проезд, МИН / МАКС / СРЗНАЧ
A11: 4.2 | B11: Абитуриенты, функция ЕСЛИ
A12: 5.1 | B12: Консолидация данных
A13: 5.2 | B13: Список студентов и свод по группам
A14: 6.1 | B14: Футбольная лига, ВПР
... A23: 9.2 | B23: Сводная таблица расходов

Sheet 1.1 Продажи авто
A1: Продажи автомобилей в России за январь 2012 г.
A3: Марка | B3: Кол-во проданных автомобилей
A4: LADA | B4: 29034
A5: KIA | B5: 11009
A6: RENAULT | B6: 10909
A7: NISSAN | B7: 10780
A8: HYUNDAI | B8: 10808
A9: CHEVROLET | B9: 9787
A10: VOLKSWAGEN | B10: 9298
A11: итого | B11: =SUM(B4:B10)

Sheet 1.2 Сортировка
A1: Продажи автомобилей в России за январь 2012 г.
A3: Марка | B3: Кол-во проданных автомобилей
A4: LADA | B4: 29034
A5: KIA | B5: 11009
A6: RENAULT | B6: 10909
A7: HYUNDAI | B7: 10808
A8: NISSAN | B8: 10780
A9: CHEVROLET | B9: 9787
A10: VOLKSWAGEN | B10: 9298
A11: итого | B11: =SUM(B4:B10)

Sheet 2.1 Три диаграммы
A1: 1) Выпуск специалистов по направлениям, тыс. чел.
A2: Направление | B2: 2006 | C2: 2005 | D2: 2004
A3: экономика и управление | B3: 325.6 | C3: 292.7 | D3: 269.9
A4: гуманитарные науки | B4: 160.3 | C4: 145.1 | D4: 144.7
A5: образование и педагогика | B5: 125.3 | C5: 129 | D5: 127.5
A6: сельское и рыбное хозяйство | B6: 36.9 | C6: 34.8 | D6: 32.7
A7: архитектура и строительство | B7: 31.8 | C7: 29.4 | D7: 26.6
A8: здравоохранение | B8: 31 | C8: 28.2 | D8: 26.8
A9: транспортные средства | B9: 30.4 | C9: 29.4 | D9: 26.1
A10: металлургия, машиностроение и металлообработка | B10: 26.5 | C10: 25.8 | D10: 23.4
A11: энергетика, энергетическое машиностроение и электротехника | B11: 23.4 | C11: 22 | D11: 19.9
A12: информатика и вычислительная техника | B12: 20.5 | C12: 17.7 | D12: 17.5
A15: 2) Страны-участники (доли, %)
A16: Страна | B16: Доля
A17: Россия | B17: 0.48
A18: Англия | B18: 0.25
A19: США | B19: 0.15
A20: Остальные | B20: 0.12
A23: 3) Объём продаж в спортивном магазине, шт.
B24: Коньки | C24: Сноуборды | D24: Велосипеды | E24: Мячи
A25: Зима | B25: 150 | C25: 140 | D25: 50 | E25: 40
A26: Весна | B26: 50 | C26: 70 | D26: 100 | E26: 60
A27: Лето | B27: 5 | C27: 30 | D27: 135 | E27: 100
A28: Осень | B28: 80 | C28: 90 | D28: 70 | E28: 80

Sheet 2.2 Выпускники вузов
A1: Таблица. КОЛИЧЕСТВО И СПЕЦИАЛИЗАЦИЯ ВЫПУСКНИКОВ РОССИЙСКИХ ВУЗОВ в 1900-1913
A2: Специальность | B2: 1900-1908 | C2: 1909-1913 | D2: 1913 | E2: Всего за 1900-1913
A3: Юристы | B3: 11598 | C3: 14491 | D3: 2624 | E3: =B3+C3
A4: Врачи | B4: 7640 | C4: 8351 | D4: 2042 | E4: =B4+C4
A5: Педагоги | B5: 6174 | C5: 8402 | D5: 1747 | E5: =B5+C5
A6: Офицеры | B6: 1976 | C6: 1467 | D6: 444 | E6: =B6+C6
A7: Священнослужители | B7: 2264 | C7: 1208 | D7: 236 | E7: =B7+C7
A8: Востоковеды | B8: 402 | C8: 313 | D8: 53 | E8: =B8+C8
A9: Инженеры фабрично-заводского производства | B9: 4650 | C9: 4452 | D9: 1277 | E9: =B9+C9
A10: Инженеры путей сообщения | B10: 1364 | C10: 939 | D10: 208 | E10: =B10+C10
A11: Горные инженеры | B11: 624 | C11: 623 | D11: 166 | E11: =B11+C11
A12: Инженеры строители, архитекторы | B12: 799 | C12: 561 | D12: 105 | E12: =B12+C12
A13: Инженеры связи | B13: 169 | C13: 201 | D13: 65 | E13: =B13+C13
A14: Экономисты | B14: 448 | C14: 762 | D14: 180 | E14: =B14+C14
... A16: Художники ваятели | B16: 177 | C16: 48 | D16: 19 | E16: =B16+C16

Sheet 3.1 Поступление
A1: Поступление на факультет Вычислительной математики и кибернетики
A3: № | B3: Фамилия | C3: Имя | D3: Отчество | E3: Город | F3: Математика | G3: Русский | H3: Информатика | I3: Общий балл
A4: 2 | B4: Караваева | C4: Анна | D4: Сергеевна | E4: Новгород | F4: 78 | G4: 94 | H4: 92 | I4: =SUM(F4:H4)
A5: 6 | B5: Челубеева | C5: Аглая | D5: Петровна | E5: Сергач | F5: 70 | G5: 94 | H5: 95 | I5: =SUM(F5:H5)
A6: 3 | B6: Солодова | C6: Светлана | D6: Викторовна | E6: Воронеж | F6: 69 | G6: 100 | H6: 85 | I6: =SUM(F6:H6)
A7: 1 | B7: Загосин | C7: Михаил | D7: Юрьевич | E7: Тула | F7: 75 | G7: 84 | H7: 88 | I7: =SUM(F7:H7)
A8: 4 | B8: Костин | C8: Вячеслав | D8: Николаевич | E8: Рязань | F8: 65 | G8: 88 | H8: 88 | I8: =SUM(F8:H8)
A9: 5 | B9: Денисов | C9: Карп | D9: Савельевич | E9: Иваново | F9: 73 | G9: 65 | H9: 100 | I9: =SUM(F9:H9)
A10: 7 | B10: Поляков | C10: Виктор | D10: Семенович | E10: Калуга | F10: 68 | G10: 69 | H10: 70 | I10: =SUM(F10:H10)
A12: Отсортировано по общему баллу (по убыванию).

Sheet 3.2 Список группы
A1: Фамилия | B1: Имя | C1: Отчество | D1: Город | E1: Телефон | G1: Фильтр по городу: оставлены только иногородние (Самара скрыта).
A2: Гражданкина | B2: Анастасия | C2: Дмитриевна | D2: Самара | E2: 8 (927) 214-35-08
A3: Ермолаева | B3: Полина | C3: Игоревна | D3: Тольятти | E3: 8 (937) 551-20-17
A4: Захаров | B4: Артём | C4: Олегович | D4: Самара | E4: 8 (917) 103-46-92
A5: Ильина | B5: Виктория | C5: Андреевна | D5: Сызрань | E5: 8 (960) 819-07-33
A6: Коротков | B6: Никита | C6: Сергеевич | D6: Самара | E6: 8 (902) 330-61-45
A7: Лукьянова | B7: Дарья | C7: Романовна | D7: Новокуйбышевск | E7: 8 (927) 698-12-70
A8: Мельников | B8: Данил | C8: Павлович | D8: Чапаевск | E8: 8 (937) 047-83-26
A9: Назарова | B9: Екатерина | C9: Алексеевна | D9: Самара | E9: 8 (917) 772-54-19
A10: Орлов | B10: Кирилл | C10: Дмитриевич | D10: Тольятти | E10: 8 (987) 265-90-31
A11: Панина | B11: Софья | C11: Михайловна | D11: Самара | E11: 8 (960) 458-37-64

Sheet 3.3 План поставки
A1: План поставки трубной продукции
A3: № п/п | B3: Наименование поставщика | C3: Диаметр (в м) | D3: Цена в руб. за 1 м | E3: в том числе по месяцам | Q3: Стоимость продукции за год в руб.
E4: Январь | F4: Февраль | G4: Март | H4: Апрель | I4: Май | J4: Июнь | K4: Июль | L4: Август | M4: Сентябрь | N4: Октябрь | O4: Ноябрь | P4: Декабрь
A5: 1 | B5: Трубзавод1 | C5: 20 | D5: 50000 | E5: 20 | F5: 21 | G5: 10 | H5: 15 | I5: 34 | J5: 16 | K5: 17 | L5: 12 | M5: 32 | N5: 10 | O5: 11 | P5: 23 | Q5: =D5*SUM(E5:P5)
A6: 2 | B6: Трубзавод 2 | C6: 30 | D6: 78000 | E6: 56 | F6: 33 | G6: 23 | H6: 24 | I6: 46 | J6: 12 | K6: 24 | L6: 56 | M6: 10 | N6: 16 | O6: 13 | P6: 12 | Q6: =D6*SUM(E6:P6)
A7: 3 | B7: Трубзавод 3 | C7: 55 | D7: 85000 | E7: 14 | F7: 23 | G7: 15 | H7: 17 | I7: 27 | J7: 11 | K7: 16 | L7: 11 | M7: 10 | N7: 20 | O7: 22 | P7: 26 | Q7: =D7*SUM(E7:P7)

Sheet 4.1 Цены на проезд
B1: Москва | C1: Санкт-Петербург | D1: Казань | E1: Минимальная цена | F1: Максимальная цена
A2: Автобус | B2: 26 | C2: 24 | D2: 16 | E2: =MIN(B2:D2) | F2: =MAX(B2:D2)
A3: Троллейбус | B3: 23 | C3: 20 | D3: 12 | E3: =MIN(B3:D3) | F3: =MAX(B3:D3)
A4: Трамвай | B4: 20 | C4: 18 | D4: 12 | E4: =MIN(B4:D4) | F4: =MAX(B4:D4)
A5: Метро | B5: 30 | C5: 22 | D5: 18 | E5: =MIN(B5:D5) | F5: =MAX(B5:D5)
A6: Средняя цена за одну поездку в трех городах | D6: =AVERAGE(B2:D5)

Sheet 4.2 Абитуриенты
A1: Фамилия | B1: Количество баллов за экзамен | E1: проходной балл
B2: русский язык | C2: математика | D2: физика | E2: 194
A3: Смирнов | B3: 81 | C3: 66 | D3: 59 | F3: =IF(SUM(B3:D3)>=$E$2,"рекомендован","резерв") | G3: =IF(F3="рекомендован",1,0)
A4: Иванов | B4: 52 | C4: 73 | D4: 47 | F4: =IF(SUM(B4:D4)>=$E$2,"рекомендован","резерв") | G4: =IF(F4="рекомендован",1,0)
A5: Кузнецов | B5: 90 | C5: 76 | D5: 69 | F5: =IF(SUM(B5:D5)>=$E$2,"рекомендован","резерв") | G5: =IF(F5="рекомендован",1,0)
A6: Соколов | B6: 65 | C6: 71 | D6: 88 | F6: =IF(SUM(B6:D6)>=$E$2,"рекомендован","резерв") | G6: =IF(F6="рекомендован",1,0)
A7: Попов | B7: 65 | C7: 73 | D7: 56 | F7: =IF(SUM(B7:D7)>=$E$2,"рекомендован","резерв") | G7: =IF(F7="рекомендован",1,0)
F8: Количество: | G8: =SUM(G3:G7)

Sheet 5.1 Консолидация
A1: имя | B1: год | C1: рост | E1: Консолидация (рост по годам)
A2: Василий | B2: 93 | C2: 165 | F2: 93 | G2: 94 | H2: 95 | I2: 96
A3: Василий | B3: 94 | C3: 169 | E3: Василий | F3: =SUMIFS($C$2:$C$9,$A$2:$A$9,$E3,$B$2:$B$9,F$2) | G3: =SUMIFS($C$2:$C$9,$A$2:$A$9,$E3,$B$2:$B$9,G$2) | H3: =SUMIFS($C$2:$C$9,$A$2:$A$9,$E3,$B$2:$B$9,H$2) | I3: =SUMIFS($C$2:$C$9,$A$2:$A$9,$E3,$B$2:$B$9,I$2)
A4: Илья | B4: 93 | C4: 157 | E4: Илья | F4: =SUMIFS($C$2:$C$9,$A$2:$A$9,$E4,$B$2:$B$9,F$2) | G4: =SUMIFS($C$2:$C$9,$A$2:$A$9,$E4,$B$2:$B$9,G$2) | H4: =SUMIFS($C$2:$C$9,$A$2:$A$9,$E4,$B$2:$B$9,H$2) | I4: =SUMIFS($C$2:$C$9,$A$2:$A$9,$E4,$B$2:$B$9,I$2)
A5: Василий | B5: 95 | C5: 170
A6: Илья | B6: 94 | C6: 160
A7: Илья | B7: 95 | C7: 163
A8: Василий | B8: 96 | C8: 174
A9: Илья | B9: 96 | C9: 165

Sheet 5.2 Список студентов
A1: № для подсчета | B1: Ф.И.О. | C1: год рождения | D1: группа
A2: 1 | B2: Афанасьев Александр | C2: 90 | D2: 903
A3: 1 | B3: Авдеев Олег | C3: 90 | D3: 903
A4: 1 | B4: Калмыков Илья | C4: 90 | D4: 903
A5: 1 | B5: Марфина Галия | C5: 90 | D5: 905
A6: 1 | B6: Киселев Сергей | C6: 91 | D6: 904
A7: 1 | B7: Гайсин Ринат | C7: 91 | D7: 904
A8: 1 | B8: Красильникова Евгения | C8: 91 | D8: 904
A9: 1 | B9: Григорьева Елена | C9: 91 | D9: 905
A10: 1 | B10: Салихова Наиля | C10: 92 | D10: 903
A11: 1 | B11: Матвеев Максим | C11: 92 | D11: 904
A12: 1 | B12: Александрова Анастасия | C12: 92 | D12: 904
A13: 1 | B13: Журавлева Анастасия | C13: 92 | D13: 904
... A21: 1 | B21: Дегтярёва Ксения | C21: 94 | D21: 904

Sheet 5.2 Свод по группам
B1: 90 | C1: 91 | D1: 92 | E1: 93 | F1: 94
A2: 903 | B2: =SUMIFS('5.2 Список студентов'!$A$2:$A$21,'5.2 Список студентов'!$C$2:$C$21,B$1,'5.2 Список студентов'!$D$2:$D$21,$A2) | C2: =SUMIFS('5.2 Список студентов'!$A$2:$A$21,'5.2 Список студентов'!$C$2:$C$21,C$1,'5.2 Список студентов'!$D$2:$D$21,$A2) | D2: =SUMIFS('5.2 Список студентов'!$A$2:$A$21,'5.2 Список студентов'!$C$2:$C$21,D$1,'5.2 Список студентов'!$D$2:$D$21,$A2) | E2: =SUMIFS('5.2 Список студентов'!$A$2:$A$21,'5.2 Список студентов'!$C$2:$C$21,E$1,'5.2 Список студентов'!$D$2:$D$21,$A2) | F2: =SUMIFS('5.2 Список студентов'!$A$2:$A$21,'5.2 Список студентов'!$C$2:$C$21,F$1,'5.2 Список студентов'!$D$2:$D$21,$A2)
A3: 904 | B3: =SUMIFS('5.2 Список студентов'!$A$2:$A$21,'5.2 Список студентов'!$C$2:$C$21,B$1,'5.2 Список студентов'!$D$2:$D$21,$A3) | C3: =SUMIFS('5.2 Список студентов'!$A$2:$A$21,'5.2 Список студентов'!$C$2:$C$21,C$1,'5.2 Список студентов'!$D$2:$D$21,$A3) | D3: =SUMIFS('5.2 Список студентов'!$A$2:$A$21,'5.2 Список студентов'!$C$2:$C$21,D$1,'5.2 Список студентов'!$D$2:$D$21,$A3) | E3: =SUMIFS('5.2 Список студентов'!$A$2:$A$21,'5.2 Список студентов'!$C$2:$C$21,E$1,'5.2 Список студентов'!$D$2:$D$21,$A3) | F3: =SUMIFS('5.2 Список студентов'!$A$2:$A$21,'5.2 Список студентов'!$C$2:$C$21,F$1,'5.2 Список студентов'!$D$2:$D$21,$A3)
A4: 905 | B4: =SUMIFS('5.2 Список студентов'!$A$2:$A$21,'5.2 Список студентов'!$C$2:$C$21,B$1,'5.2 Список студентов'!$D$2:$D$21,$A4) | C4: =SUMIFS('5.2 Список студентов'!$A$2:$A$21,'5.2 Список студентов'!$C$2:$C$21,C$1,'5.2 Список студентов'!$D$2:$D$21,$A4) | D4: =SUMIFS('5.2 Список студентов'!$A$2:$A$21,'5.2 Список студентов'!$C$2:$C$21,D$1,'5.2 Список студентов'!$D$2:$D$21,$A4) | E4: =SUMIFS('5.2 Список студентов'!$A$2:$A$21,'5.2 Список студентов'!$C$2:$C$21,E$1,'5.2 Список студентов'!$D$2:$D$21,$A4) | F4: =SUMIFS('5.2 Список студентов'!$A$2:$A$21,'5.2 Список студентов'!$C$2:$C$21,F$1,'5.2 Список студентов'!$D$2:$D$21,$A4)
A6: В тетради предлагалось суммировать ячейки трёхмерными ссылками; здесь то же самое сделано через СУММЕСЛИМН по списку.

Sheet 6.1 Футбол ВПР
A1: РОССИЙСКАЯ ФУТБОЛЬНАЯ ПРЕМЬЕР ЛИГА
A2: Команда | B2: Город | C2: Главный тренер | D2: Бюджет (Млн. $) | E2: Коэффициент УЕФА | F2: Место
A3: Зенит | B3: Санкт-Петербург | C3: Лучиано Спаллетти | D3: 102 | E3: 60.941 | F3: 1
A4: ЦСКА | B4: Москва | C4: Леонид Слуцкий | D4: 70 | E4: 73.941 | F4: 2
A5: Рубин | B5: Казань | C5: Курбан Бердыев | D5: 68 | E5: 31.941 | F5: 6
A6: Спартак | B6: Москва | C6: Валерий Карпин | D6: 85 | E6: 51.941 | F6: 5
A7: Локомотив | B7: Москва | C7: Жозе Коусейру | D7: 90 | E7: 18.441 | F7: 3
A8: Спартак Н | B8: Нальчик | C8: Сергей Ташуев | D8: 15 | E8: 8.941 | F8: 16
A9: Динамо | B9: Москва | C9: Сергей Силкин | D9: 80 | E9: 10.441 | F9: 4
A10: Томь | B10: Томск | C10: Сергей Передня | D10: 28 | E10: 3.624 | F10: 15
A11: Ростов | B11: Ростов-на-Дону | C11: Сергей Балахнин | D11: 28 | E11: 2.899 | F11: 11
A12: Анжи | B12: Махачкала | C12: Гус Хиддинк | D12: 125 | E12: 2.875 | F12: 7
A13: Краснодар | B13: Краснодар | C13: Славолюб Муслин | D13: 40 | E13: 2.887 | F13: 9
A14: Терек | B14: Грозный | C14: Станислав Черчесов | D14: 50 | E14: 1.004 | F14: 12
... A18: Волга | B18: Нижний Новгород | C18: Дмитрий Черышев | D18: 32 | E18: 10.441 | F18: 13
A21: Поиск
A22: Команда | B22: Локомотив | E22: ← выберите команду из списка
A23: Город | B23: =VLOOKUP($B$22,$A$3:$F$18,2,FALSE)
A24: Главный тренер | B24: =VLOOKUP($B$22,$A$3:$F$18,3,FALSE)
A25: Бюджет (Млн. $) | B25: =VLOOKUP($B$22,$A$3:$F$18,4,FALSE)
A26: Коэффициент УЕФА | B26: =VLOOKUP($B$22,$A$3:$F$18,5,FALSE)
A27: Место | B27: =VLOOKUP($B$22,$A$3:$F$18,6,FALSE)

Sheet 6.2 Продажи ПК
A1: Месяц | B1: Продано ноутбуков | C1: Продано настольных ПК
A2: Январь | B2: 41 | C2: 52
A3: Февраль | B3: 54 | C3: 61
A4: Март | B4: 65 | C4: 65
A5: Апрель | B5: 70 | C5: 60
A6: Май | B6: 60 | C6: 55
A7: Июнь | B7: 40 | C7: 60

Sheet 7.1 Шаблон счёта
A1: лицевой счет № | E1: СЧЕТ | G1: ДЕЙСТВИТЕЛЕН ДО | H1: __.__.____ г. | K1: ФАКТУРА
A2: за | E2: общая площадь помещения | I2: кв.м | J2: количество проживающих:
K3: Оплатить не позднее __.__.____
A5: № | B5: Краткое наименование услуги | C5: Оплата, поступившая в предыдущем месяце (руб.) | D5: Перерасчет за предыдущий период (руб.) | E5: Долг(+), переплата(-) (руб.) | F5: Единица измерения | G5: Объём | H5: Тариф за единицу услуги (руб.) | I5: Начислено за месяц по тарифу (руб.) | J5: Сумма недопоставки (руб.) | K5: К оплате с учётом недопоставки (руб.)
A6: 1 | B6: 2 | C6: 3 | D6: 4 | E6: 5 | F6: 6 | G6: 7 | H6: 8 | I6: 9 | J6: 10 | K6: 11
A7: 1 | B7: Электроснабжение | F7: кВт*ч | I7: =G7*H7 | K7: =I7-J7
A8: 2 | B8: Отопление | F8: кв.метр | I8: =G8*H8 | K8: =I8-J8
A9: 3 | B9: Горячее водоснабжение | F9: куб.м | I9: =G9*H9 | K9: =I9-J9
B10: в т.ч. холодная вода для нужд ГВС | F10: куб.м | I10: =G10*H10 | K10: =I10-J10
B11: в т.ч. подогрев воды | F11: куб.м | I11: =G11*H11 | K11: =I11-J11
A12: 4 | B12: Водоснабжение | F12: куб.м | I12: =G12*H12 | K12: =I12-J12
A13: 5 | B13: Канализование | F13: куб.м | I13: =G13*H13 | K13: =I13-J13
B14: Итого по коммунальным услугам | C14: =C7+C8+C9+C12+C13 | D14: =D7+D8+D9+D12+D13 | E14: =E7+E8+E9+E12+E13 | I14: =I7+I8+I9+I12+I13 | J14: =J7+J8+J9+J12+J13 | K14: =K7+K8+K9+K12+K13
A15: 6 | B15: Наем | F15: кв.метр | I15: =G15*H15 | K15: =I15-J15
A16: 7 | B16: Капитальный ремонт жилых зданий | F16: кв.метр | I16: =G16*H16 | K16: =I16-J16
A17: 8 | B17: Управление домом | F17: кв.метр | I17: =G17*H17 | K17: =I17-J17
A18: 9 | B18: Уборка придомовой территории | F18: кв.метр | I18: =G18*H18 | K18: =I18-J18
A19: 10 | B19: Вывоз твердых бытовых отходов | F19: кв.метр | I19: =G19*H19 | K19: =I19-J19
A20: 11 | B20: Содержание контейнерных площадок | F20: кв.метр | I20: =G20*H20 | K20: =I20-J20
B21: Тех. обслуживание и тек. ремонт
A22: 12 | B22: нежилого здания | F22: кв.метр | I22: =G22*H22 | K22: =I22-J22
A23: 13 | B23: внутридомовых систем водоснабж. и кан. | F23: кв.метр | I23: =G23*H23 | K23: =I23-J23
A24: 14 | B24: внутридомовых систем центр. отопления | F24: кв.метр | I24: =G24*H24 | K24: =I24-J24
A25: 15 | B25: внутридомовых сетей эл. снаб. и эл. обор. | F25: кв.метр | I25: =G25*H25 | K25: =I25-J25
B26: Итого по жилищным услугам | C26: =C15+C16+C17+C18+C19+C20+C22+C23+C24+C25 | D26: =D15+D16+D17+D18+D19+D20+D22+D23+D24+D25 | E26: =E15+E16+E17+E18+E19+E20+E22+E23+E24+E25 | I26: =I15+I16+I17+I18+I19+I20+I22+I23+I24+I25 | J26: =J15+J16+J17+J18+J19+J20+J22+J23+J24+J25 | K26: =K15+K16+K17+K18+K19+K20+K22+K23+K24+K25
B35: Итого | C35: =C14+C26 | D35: =D14+D26 | E35: =E14+E26 | I35: =I14+I26 | J35: =J14+J26 | K35: =K14+K26

Sheet 7.2 Счёт-фактура
A1: лицевой счет № | C1: 2765896 | E1: СЧЕТ | G1: ДЕЙСТВИТЕЛЕН ДО | H1: 30.04.2012 г. | K1: ФАКТУРА
A2: за | C2: апрель 2012 | E2: общая площадь помещения | H2: 59.9 | I2: кв.м | J2: количество проживающих: | L2: 2
K3: Оплатить не позднее 30.04.2012
A5: № | B5: Краткое наименование услуги | C5: Оплата, поступившая в предыдущем месяце (руб.) | D5: Перерасчет за предыдущий период (руб.) | E5: Долг(+), переплата(-) (руб.) | F5: Единица измерения | G5: Объём | H5: Тариф за единицу услуги (руб.) | I5: Начислено за месяц по тарифу (руб.) | J5: Сумма недопоставки (руб.) | K5: К оплате с учётом недопоставки (руб.)
A6: 1 | B6: 2 | C6: 3 | D6: 4 | E6: 5 | F6: 6 | G6: 7 | H6: 8 | I6: 9 | J6: 10 | K6: 11
A7: 1 | B7: Электроснабжение | C7: 346.5 | F7: кВт*ч | G7: 278 | H7: 2.43 | I7: =G7*H7 | K7: =I7-J7
A8: 2 | B8: Отопление | C8: 1224.38 | F8: кв.метр | G8: 59.9 | H8: 22.28 | I8: =G8*H8 | K8: =I8-J8
A9: 3 | B9: Горячее водоснабжение | C9: 1152.32 | F9: куб.м | G9: 13.8 | H9: 83.55 | I9: =G9*H9 | K9: =I9-J9
B10: в т.ч. холодная вода для нужд ГВС | C10: 202.8 | F10: куб.м | G10: 13.8 | H10: 14.69 | I10: =G10*H10 | K10: =I10-J10
B11: в т.ч. подогрев воды | C11: 189.2 | F11: куб.м | G11: 13.8 | H11: 68.86 | I11: =G11*H11 | K11: =I11-J11
A12: 4 | B12: Водоснабжение | C12: 400.4 | F12: куб.м | G12: 27 | H12: 14.69 | I12: =G12*H12 | K12: =I12-J12
A13: 5 | B13: Канализование | C13: 450.69 | F13: куб.м | G13: 40.8 | H13: 11.2 | I13: =G13*H13 | K13: =I13-J13
B14: Итого по коммунальным услугам | C14: =C7+C8+C9+C12+C13 | D14: =D7+D8+D9+D12+D13 | E14: =E7+E8+E9+E12+E13 | I14: =I7+I8+I9+I12+I13 | J14: =J7+J8+J9+J12+J13 | K14: =K7+K8+K9+K12+K13
A15: 6 | B15: Наем | C15: 0 | F15: кв.метр | G15: 0 | H15: 0 | I15: =G15*H15 | K15: =I15-J15
A16: 7 | B16: Капитальный ремонт жилых зданий | C16: 297.32 | F16: кв.метр | G16: 59.9 | H16: 5 | I16: =G16*H16 | K16: =I16-J16
A17: 8 | B17: Управление домом | C17: 141.53 | F17: кв.метр | G17: 59.9 | H17: 2.38 | I17: =G17*H17 | K17: =I17-J17
A18: 9 | B18: Уборка придомовой территории | C18: 152.83 | F18: кв.метр | G18: 59.9 | H18: 2.57 | I18: =G18*H18 | K18: =I18-J18
A19: 10 | B19: Вывоз твердых бытовых отходов | C19: 130.82 | F19: кв.метр | G19: 59.9 | H19: 2.2 | I19: =G19*H19 | K19: =I19-J19
A20: 11 | B20: Содержание контейнерных площадок | C20: 16.65 | F20: кв.метр | G20: 59.9 | H20: 0.28 | I20: =G20*H20 | K20: =I20-J20
B21: Тех. обслуживание и тек. ремонт
A22: 12 | B22: нежилого здания | C22: 114.5 | F22: кв.метр | G22: 59.9 | H22: 2.43 | I22: =G22*H22 | K22: =I22-J22
A23: 13 | B23: внутридомовых систем водоснабж. и кан. | C23: 115.96 | F23: кв.метр | G23: 59.9 | H23: 1.95 | I23: =G23*H23 | K23: =I23-J23
A24: 14 | B24: внутридомовых систем центр. отопления | C24: 83.25 | F24: кв.метр | G24: 59.9 | H24: 1.4 | I24: =G24*H24 | K24: =I24-J24
A25: 15 | B25: внутридомовых сетей эл. снаб. и эл. обор. | C25: 48.76 | F25: кв.метр | G25: 59.9 | H25: 0.82 | I25: =G25*H25 | K25: =I25-J25
B26: Итого по жилищным услугам | C26: =C15+C16+C17+C18+C19+C20+C22+C23+C24+C25 | D26: =D15+D16+D17+D18+D19+D20+D22+D23+D24+D25 | E26: =E15+E16+E17+E18+E19+E20+E22+E23+E24+E25 | I26: =I15+I16+I17+I18+I19+I20+I22+I23+I24+I25 | J26: =J15+J16+J17+J18+J19+J20+J22+J23+J24+J25 | K26: =K15+K16+K17+K18+K19+K20+K22+K23+K24+K25
B35: Итого | C35: =C14+C26 | D35: =D14+D26 | E35: =E14+E26 | I35: =I14+I26 | J35: =J14+J26 | K35: =K14+K26

Sheet 8.1 Коттеджи
B1: Стоимость коттеджей
B3: тариф | C3: 1000
A4: площадь коттеджа (кв м) | C4: 100
B6: метраж | C6: =C3*C4*C17
B7: 100 | C7: =$C$3*B7*$C$17
B8: 150 | C8: =$C$3*B8*$C$17
B9: 200 | C9: =$C$3*B9*$C$17
B10: 250 | C10: =$C$3*B10*$C$17
B11: 300 | C11: =$C$3*B11*$C$17
B12: 350 | C12: =$C$3*B12*$C$17
B13: 400 | C13: =$C$3*B13*$C$17
B14: 450 | C14: =$C$3*B14*$C$17
B15: 500 | C15: =$C$3*B15*$C$17
A17: Курс доллара | C17: 28.1

Sheet 8.2 Что-если
A1: Занятая сумма | B1: 100000
A2: Срок (мес.) | B2: 10
A3: Процентная ставка | B3: 0.05
A4: Сумма к возврату | B4: =B1*(1+B3*B2)
A6: Подбор параметра: ячейка B4 → 150 000, изменяя B3. Получилась ставка 5% в месяц.

Sheet 8.3 Сценарии
A1: Прибыль от магазина одежды | B1: 50000
A2: Прибыль от ресторана | B2: 50000
A3: Прибыль от салона красоты | B3: 50000
A4: Расход на всех сотрудников | B4: 30000
A5: Общий доход | B5: =SUM(B1:B3)-B4
A8: Сводка по сценариям
B9: Нормальная работа | C9: Разорение | D9: Процветание
A10: Прибыль от магазина одежды | B10: 50000 | C10: 8000 | D10: 85000
A11: Прибыль от ресторана | B11: 50000 | C11: 5000 | D11: 90000
A12: Прибыль от салона красоты | B12: 50000 | C12: 7000 | D12: 70000
A13: Расход на всех сотрудников | B13: 30000 | C13: 30000 | D13: 40000
A14: Общий доход | B14: =SUM(B10:B12)-B13 | C14: =SUM(C10:C12)-C13 | D14: =SUM(D10:D12)-D13
A16: Значения в B1:B4 — сценарий «Нормальная работа». Остальные два набора значений записаны в сводке выше.

Sheet 8.4 Поиск решения
A1: Подарки на 8 марта
A3: Покупки | B3: Кол-во | C3: Цена | D3: Общая стоимость
A4: Букет тюльпанов | B4: 10 | C4: 500 | D4: =B4*C4
A5: Духи Chanel | B5: 5 | C5: 2000 | D5: =B5*C5
A6: Подарочный сертификат | B6: 3 | C6: 1000 | D6: =B6*C6
A7: Шоколадные конфеты | B7: =2*B4 | C7: 150 | D7: =B7*C7
A8: Итого | D8: =SUM(D4:D7)
A10: Поиск решения: цель D8 = 21 000, изменяя B4; B7 = 2·B4 (конфет вдвое больше тюльпанов). Получилось 10 букетов и 20 коробок конфет.

Sheet 9.1 Абоненты
A1: Абоненты | B1: Лицевой счет
A2: Смирнов Алексей | B2: 103389230
A3: Петров Петр | B3: 103546372
A4: Сидоров Марат | B4: 105664835

Sheet 9.1 Тарифы
A1: Стоимость трафика на внутренние ресурсы (1 мб) | B1: Стоимость трафика внешние ресурсы (1 мб)
A2: 0.5 | B2: 1.5

Sheet 9.1 Трафик
A1: Абоненты | B1: Дата | C1: Количество исходящего трафика на внутренние ресурсы (в мб) | D1: Количество исходящего трафика на внешние ресурсы (в мб)
A2: Смирнов Алексей | B2: 40330 | C2: 13 | D2: 2
A3: Смирнов Алексей | B3: 40331 | C3: 21 | D3: 0
A4: Смирнов Алексей | B4: 40332 | C4: 1 | D4: 1
A5: Смирнов Алексей | B5: 40333 | C5: 19 | D5: 0
A6: Смирнов Алексей | B6: 40334 | C6: 5 | D6: 0
A7: Смирнов Алексей | B7: 40335 | C7: 1 | D7: 23
A8: Смирнов Алексей | B8: 40336 | C8: 0.5 | D8: 0
A9: Смирнов Алексей | B9: 40337 | C9: 6 | D9: 0
A10: Смирнов Алексей | B10: 40338 | C10: 0.5 | D10: 0
A11: Смирнов Алексей | B11: 40339 | C11: 2 | D11: 4.5
A12: Смирнов Алексей | B12: 40340 | C12: 0 | D12: 15
A13: Смирнов Алексей | B13: 40341 | C13: 0 | D13: 4.5
... A91: Сидоров Марат | B91: 40359 | C91: 19 | D91: 3

Sheet 9.2 Сводная
A3: Сумма по полю Количество исходящего трафика на внутренние ресурсы (мб)
A4: Названия строк | B4: 40330 | C4: 40331 | D4: 40332 | E4: 40333 | F4: 40334 | G4: 40335 | H4: 40336 | I4: 40337 | J4: 40338 | K4: 40339 | L4: 40340 | M4: 40341 | N4: 40342 | O4: 40343 | P4: 40344 | Q4: 40345 | R4: 40346 | S4: 40347 | T4: 40348 | U4: 40349 | V4: 40350 | W4: 40351 | X4: 40352 | Y4: 40353 | Z4: 40354 | AA4: 40355 | AB4: 40356 | AC4: 40357 | AD4: 40358 | AE4: 40359 | AF4: Итого
A5: Петров Петр | B5: =SUMIFS('9.1 Трафик'!$C$2:$C$91,'9.1 Трафик'!$A$2:$A$91,$A5,'9.1 Трафик'!$B$2:$B$91,B$4) | C5: =SUMIFS('9.1 Трафик'!$C$2:$C$91,'9.1 Трафик'!$A$2:$A$91,$A5,'9.1 Трафик'!$B$2:$B$91,C$4) | D5: =SUMIFS('9.1 Трафик'!$C$2:$C$91,'9.1 Трафик'!$A$2:$A$91,$A5,'9.1 Трафик'!$B$2:$B$91,D$4) | E5: =SUMIFS('9.1 Трафик'!$C$2:$C$91,'9.1 Трафик'!$A$2:$A$91,$A5,'9.1 Трафик'!$B$2:$B$91,E$4) | F5: =SUMIFS('9.1 Трафик'!$C$2:$C$91,'9.1 Трафик'!$A$2:$A$91,$A5,'9.1 Трафик'!$B$2:$B$91,F$4) | G5: =SUMIFS('9.1 Трафик'!$C$2:$C$91,'9.1 Трафик'!$A$2:$A$91,$A5,'9.1 Трафик'!$B$2:$B$91,G$4) | H5: =SUMIFS('9.1 Трафик'!$C$2:$C$91,'9.1 Трафик'!$A$2:$A$91,$A5,'9.1 Трафик'!$B$2:$B$91,H$4) | I5: =SUMIFS('9.1 Трафик'!$C$2:$C$91,'9.1 Трафик'!$A$2:$A$91,$A5,'9.1 Трафик'!$B$2:$B$91,I$4) | ... AE5: =SUMIFS('9.1 Трафик'!$C$2:$C$91,'9.1 Трафик'!$A$2:$A$91,$A5,'9.1 Трафик'!$B$2:$B$91,AE$4) | AF5: =SUM(B5:AE5)
A6: Сидоров Марат | B6: =SUMIFS('9.1 Трафик'!$C$2:$C$91,'9.1 Трафик'!$A$2:$A$91,$A6,'9.1 Трафик'!$B$2:$B$91,B$4) | C6: =SUMIFS('9.1 Трафик'!$C$2:$C$91,'9.1 Трафик'!$A$2:$A$91,$A6,'9.1 Трафик'!$B$2:$B$91,C$4) | D6: =SUMIFS('9.1 Трафик'!$C$2:$C$91,'9.1 Трафик'!$A$2:$A$91,$A6,'9.1 Трафик'!$B$2:$B$91,D$4) | E6: =SUMIFS('9.1 Трафик'!$C$2:$C$91,'9.1 Трафик'!$A$2:$A$91,$A6,'9.1 Трафик'!$B$2:$B$91,E$4) | F6: =SUMIFS('9.1 Трафик'!$C$2:$C$91,'9.1 Трафик'!$A$2:$A$91,$A6,'9.1 Трафик'!$B$2:$B$91,F$4) | G6: =SUMIFS('9.1 Трафик'!$C$2:$C$91,'9.1 Трафик'!$A$2:$A$91,$A6,'9.1 Трафик'!$B$2:$B$91,G$4) | H6: =SUMIFS('9.1 Трафик'!$C$2:$C$91,'9.1 Трафик'!$A$2:$A$91,$A6,'9.1 Трафик'!$B$2:$B$91,H$4) | I6: =SUMIFS('9.1 Трафик'!$C$2:$C$91,'9.1 Трафик'!$A$2:$A$91,$A6,'9.1 Трафик'!$B$2:$B$91,I$4) | ... AE6: =SUMIFS('9.1 Трафик'!$C$2:$C$91,'9.1 Трафик'!$A$2:$A$91,$A6,'9.1 Трафик'!$B$2:$B$91,AE$4) | AF6: =SUM(B6:AE6)
A7: Смирнов Алексей | B7: =SUMIFS('9.1 Трафик'!$C$2:$C$91,'9.1 Трафик'!$A$2:$A$91,$A7,'9.1 Трафик'!$B$2:$B$91,B$4) | C7: =SUMIFS('9.1 Трафик'!$C$2:$C$91,'9.1 Трафик'!$A$2:$A$91,$A7,'9.1 Трафик'!$B$2:$B$91,C$4) | D7: =SUMIFS('9.1 Трафик'!$C$2:$C$91,'9.1 Трафик'!$A$2:$A$91,$A7,'9.1 Трафик'!$B$2:$B$91,D$4) | E7: =SUMIFS('9.1 Трафик'!$C$2:$C$91,'9.1 Трафик'!$A$2:$A$91,$A7,'9.1 Трафик'!$B$2:$B$91,E$4) | F7: =SUMIFS('9.1 Трафик'!$C$2:$C$91,'9.1 Трафик'!$A$2:$A$91,$A7,'9.1 Трафик'!$B$2:$B$91,F$4) | G7: =SUMIFS('9.1 Трафик'!$C$2:$C$91,'9.1 Трафик'!$A$2:$A$91,$A7,'9.1 Трафик'!$B$2:$B$91,G$4) | H7: =SUMIFS('9.1 Трафик'!$C$2:$C$91,'9.1 Трафик'!$A$2:$A$91,$A7,'9.1 Трафик'!$B$2:$B$91,H$4) | I7: =SUMIFS('9.1 Трафик'!$C$2:$C$91,'9.1 Трафик'!$A$2:$A$91,$A7,'9.1 Трафик'!$B$2:$B$91,I$4) | ... AE7: =SUMIFS('9.1 Трафик'!$C$2:$C$91,'9.1 Трафик'!$A$2:$A$91,$A7,'9.1 Трафик'!$B$2:$B$91,AE$4) | AF7: =SUM(B7:AE7)
A8: Общий итог | B8: =SUM(B5:B7) | C8: =SUM(C5:C7) | D8: =SUM(D5:D7) | E8: =SUM(E5:E7) | F8: =SUM(F5:F7) | G8: =SUM(G5:G7) | H8: =SUM(H5:H7) | I8: =SUM(I5:I7) | ... AF8: =SUM(AF5:AF7)
A11: Сумма по полю Количество исходящего трафика на внешние ресурсы (мб)
A12: Названия строк | B12: 40330 | C12: 40331 | D12: 40332 | E12: 40333 | F12: 40334 | G12: 40335 | H12: 40336 | I12: 40337 | J12: 40338 | K12: 40339 | L12: 40340 | M12: 40341 | N12: 40342 | O12: 40343 | P12: 40344 | Q12: 40345 | R12: 40346 | S12: 40347 | T12: 40348 | U12: 40349 | V12: 40350 | W12: 40351 | X12: 40352 | Y12: 40353 | Z12: 40354 | AA12: 40355 | AB12: 40356 | AC12: 40357 | AD12: 40358 | AE12: 40359 | AF12: Итого
A13: Петров Петр | B13: =SUMIFS('9.1 Трафик'!$D$2:$D$91,'9.1 Трафик'!$A$2:$A$91,$A13,'9.1 Трафик'!$B$2:$B$91,B$12) | C13: =SUMIFS('9.1 Трафик'!$D$2:$D$91,'9.1 Трафик'!$A$2:$A$91,$A13,'9.1 Трафик'!$B$2:$B$91,C$12) | D13: =SUMIFS('9.1 Трафик'!$D$2:$D$91,'9.1 Трафик'!$A$2:$A$91,$A13,'9.1 Трафик'!$B$2:$B$91,D$12) | E13: =SUMIFS('9.1 Трафик'!$D$2:$D$91,'9.1 Трафик'!$A$2:$A$91,$A13,'9.1 Трафик'!$B$2:$B$91,E$12) | F13: =SUMIFS('9.1 Трафик'!$D$2:$D$91,'9.1 Трафик'!$A$2:$A$91,$A13,'9.1 Трафик'!$B$2:$B$91,F$12) | G13: =SUMIFS('9.1 Трафик'!$D$2:$D$91,'9.1 Трафик'!$A$2:$A$91,$A13,'9.1 Трафик'!$B$2:$B$91,G$12) | H13: =SUMIFS('9.1 Трафик'!$D$2:$D$91,'9.1 Трафик'!$A$2:$A$91,$A13,'9.1 Трафик'!$B$2:$B$91,H$12) | I13: =SUMIFS('9.1 Трафик'!$D$2:$D$91,'9.1 Трафик'!$A$2:$A$91,$A13,'9.1 Трафик'!$B$2:$B$91,I$12) | ... AE13: =SUMIFS('9.1 Трафик'!$D$2:$D$91,'9.1 Трафик'!$A$2:$A$91,$A13,'9.1 Трафик'!$B$2:$B$91,AE$12) | AF13: =SUM(B13:AE13)
A14: Сидоров Марат | B14: =SUMIFS('9.1 Трафик'!$D$2:$D$91,'9.1 Трафик'!$A$2:$A$91,$A14,'9.1 Трафик'!$B$2:$B$91,B$12) | C14: =SUMIFS('9.1 Трафик'!$D$2:$D$91,'9.1 Трафик'!$A$2:$A$91,$A14,'9.1 Трафик'!$B$2:$B$91,C$12) | D14: =SUMIFS('9.1 Трафик'!$D$2:$D$91,'9.1 Трафик'!$A$2:$A$91,$A14,'9.1 Трафик'!$B$2:$B$91,D$12) | E14: =SUMIFS('9.1 Трафик'!$D$2:$D$91,'9.1 Трафик'!$A$2:$A$91,$A14,'9.1 Трафик'!$B$2:$B$91,E$12) | F14: =SUMIFS('9.1 Трафик'!$D$2:$D$91,'9.1 Трафик'!$A$2:$A$91,$A14,'9.1 Трафик'!$B$2:$B$91,F$12) | G14: =SUMIFS('9.1 Трафик'!$D$2:$D$91,'9.1 Трафик'!$A$2:$A$91,$A14,'9.1 Трафик'!$B$2:$B$91,G$12) | H14: =SUMIFS('9.1 Трафик'!$D$2:$D$91,'9.1 Трафик'!$A$2:$A$91,$A14,'9.1 Трафик'!$B$2:$B$91,H$12) | I14: =SUMIFS('9.1 Трафик'!$D$2:$D$91,'9.1 Трафик'!$A$2:$A$91,$A14,'9.1 Трафик'!$B$2:$B$91,I$12) | ... AE14: =SUMIFS('9.1 Трафик'!$D$2:$D$91,'9.1 Трафик'!$A$2:$A$91,$A14,'9.1 Трафик'!$B$2:$B$91,AE$12) | AF14: =SUM(B14:AE14)
A15: Смирнов Алексей | B15: =SUMIFS('9.1 Трафик'!$D$2:$D$91,'9.1 Трафик'!$A$2:$A$91,$A15,'9.1 Трафик'!$B$2:$B$91,B$12) | C15: =SUMIFS('9.1 Трафик'!$D$2:$D$91,'9.1 Трафик'!$A$2:$A$91,$A15,'9.1 Трафик'!$B$2:$B$91,C$12) | D15: =SUMIFS('9.1 Трафик'!$D$2:$D$91,'9.1 Трафик'!$A$2:$A$91,$A15,'9.1 Трафик'!$B$2:$B$91,D$12) | E15: =SUMIFS('9.1 Трафик'!$D$2:$D$91,'9.1 Трафик'!$A$2:$A$91,$A15,'9.1 Трафик'!$B$2:$B$91,E$12) | F15: =SUMIFS('9.1 Трафик'!$D$2:$D$91,'9.1 Трафик'!$A$2:$A$91,$A15,'9.1 Трафик'!$B$2:$B$91,F$12) | G15: =SUMIFS('9.1 Трафик'!$D$2:$D$91,'9.1 Трафик'!$A$2:$A$91,$A15,'9.1 Трафик'!$B$2:$B$91,G$12) | H15: =SUMIFS('9.1 Трафик'!$D$2:$D$91,'9.1 Трафик'!$A$2:$A$91,$A15,'9.1 Трафик'!$B$2:$B$91,H$12) | I15: =SUMIFS('9.1 Трафик'!$D$2:$D$91,'9.1 Трафик'!$A$2:$A$91,$A15,'9.1 Трафик'!$B$2:$B$91,I$12) | ... AE15: =SUMIFS('9.1 Трафик'!$D$2:$D$91,'9.1 Трафик'!$A$2:$A$91,$A15,'9.1 Трафик'!$B$2:$B$91,AE$12) | AF15: =SUM(B15:AE15)
A16: Общий итог | B16: =SUM(B13:B15) | C16: =SUM(C13:C15) | D16: =SUM(D13:D15) | E16: =SUM(E13:E15) | F16: =SUM(F13:F15) | G16: =SUM(G13:G15) | H16: =SUM(H13:H15) | I16: =SUM(I13:I15) | ... AF16: =SUM(AF13:AF15)
A19: Количество потраченных рублей в месяц | B19: =AF8*'9.1 Тарифы'!A2+AF16*'9.1 Тарифы'!B2
